{
  "project_info": {
    "project_number": "792264433154",
    "firebase_url": "https://easyfoodv1.firebaseio.com",
    "project_id": "easyfoodv1",
    "storage_bucket": "easyfoodv1.appspot.com"
  },
  "client": [
    {
      "client_info": {
        "mobilesdk_app_id": "1:792264433154:android:29c00cdca2b98af5",
        "android_client_info": {
          "package_name": "com.lexxdigital.easyfoodvone"
        }
      },
      "oauth_client": [
        {
          "client_id": "792264433154-q2dgf2vv3pmnqptee9qgd0nktvoq9qjk.apps.googleusercontent.com",
          "client_type": 1,
          "android_info": {
            "package_name": "com.lexxdigital.easyfoodvone",
            "certificate_hash": "bbabd4423ba3f48657d7359ae83fb21ee48bb9c6"
          }
        },
        {
          "client_id": "792264433154-ph9s4gvod66dhnermaucmit6jfgldopg.apps.googleusercontent.com",
          "client_type": 3
        }
      ],
      "api_key": [
        {
          "current_key": "AIzaSyCCMOfZf2T8MzWmn1FARZu-4j9e7GTowU8"
        }
      ],
      "services": {
        "analytics_service": {
          "status": 1
        },
        "appinvite_service": {
          "status": 2,
          "other_platform_oauth_client": [
            {
              "client_id": "792264433154-ph9s4gvod66dhnermaucmit6jfgldopg.apps.googleusercontent.com",
              "client_type": 3
            }
          ]
        },
        "ads_service": {
          "status": 2
        }
      }
    }
  ],
  "configuration_version": "1"
}